setup.cfg
setup.py
paparazzo/__init__.py
paparazzo/exceptions.py
paparazzo/paparazzo.py
paparazzo.egg-info/PKG-INFO
paparazzo.egg-info/SOURCES.txt
paparazzo.egg-info/dependency_links.txt
paparazzo.egg-info/top_level.txt