Metadata-Version: 1.1
Name: paparazzo
Version: 0.1.0
Summary: Paparazzo is a tool for the automation of Elasticsearch data backup and restoration, utilising Amazon's S3.
Home-page: https://github.com/ethanbray/paparazzo
Author: Ethan Bray
Author-email: e.bray@txtnation.com
License: UNKNOWN
Download-URL: https://github.com/ethanbray/paparazzo/archive/0.1.0.tar.gz
Keywords: elasticsearch,snapshot,backup
Platform: UNKNOWN
